ae_python/__init__.py
ae_python/ae_script.py
ae_python/comp.py
ae_python/compiler.py
ae_python/standalone_functions.py
ae_python-1.0.0.dist-info/LICENSE
ae_python-1.0.0.dist-info/METADATA
ae_python-1.0.0.dist-info/WHEEL
ae_python-1.0.0.dist-info/top_level.txt
ae_python-1.0.0.dist-info/RECORD
